Kivy_examples-2.2.0.data/data/share/kivy-examples/3Drendering/main.py
Kivy_examples-2.2.0.data/data/share/kivy-examples/3Drendering/monkey.obj
Kivy_examples-2.2.0.data/data/share/kivy-examples/3Drendering/objloader.py
Kivy_examples-2.2.0.data/data/share/kivy-examples/3Drendering/simple.glsl
Kivy_examples-2.2.0.data/data/share/kivy-examples/RST_Editor/editor.kv
Kivy_examples-2.2.0.data/data/share/kivy-examples/RST_Editor/main.py
Kivy_examples-2.2.0.data/data/share/kivy-examples/android/compass/android.txt
Kivy_examples-2.2.0.data/data/share/kivy-examples/android/compass/compass.kv
Kivy_examples-2.2.0.data/data/share/kivy-examples/android/compass/main.py
Kivy_examples-2.2.0.data/data/share/kivy-examples/android/compass/needle.png
Kivy_examples-2.2.0.data/data/share/kivy-examples/android/compass/rose.png
Kivy_examples-2.2.0.data/data/share/kivy-examples/android/takepicture/android.txt
Kivy_examples-2.2.0.data/data/share/kivy-examples/android/takepicture/main.py
Kivy_examples-2.2.0.data/data/share/kivy-examples/android/takepicture/shadow32.png
Kivy_examples-2.2.0.data/data/share/kivy-examples/android/takepicture/takepicture.kv
Kivy_examples-2.2.0.data/data/share/kivy-examples/animation/animate.py
Kivy_examples-2.2.0.data/data/share/kivy-examples/application/app_suite.py
Kivy_examples-2.2.0.data/data/share/kivy-examples/application/app_with_build.py
Kivy_examples-2.2.0.data/data/share/kivy-examples/application/app_with_config.py
Kivy_examples-2.2.0.data/data/share/kivy-examples/application/app_with_kv.py
Kivy_examples-2.2.0.data/data/share/kivy-examples/application/app_with_kv_in_template1.py
Kivy_examples-2.2.0.data/data/share/kivy-examples/application/test.kv
Kivy_examples-2.2.0.data/data/share/kivy-examples/application/testkvfile.kv
Kivy_examples-2.2.0.data/data/share/kivy-examples/application/app_suite_data/testkvdir.kv
Kivy_examples-2.2.0.data/data/share/kivy-examples/application/template1/test.kv
Kivy_examples-2.2.0.dist-info/AUTHORS
Kivy_examples-2.2.0.dist-info/LICENSE
Kivy_examples-2.2.0.dist-info/METADATA
Kivy_examples-2.2.0.dist-info/WHEEL
Kivy_examples-2.2.0.dist-info/dependency_links.txt
Kivy_examples-2.2.0.dist-info/top_level.txt
Kivy_examples-2.2.0.dist-info/RECORD
