Metadata-Version: 2.1
Name: Kivy-examples
Version: 2.2.0
Summary: Kivy examples.
Home-page: http://kivy.org
Author: Kivy Team and other contributors
Author-email: kivy-dev@googlegroups.com
License: MIT
Requires-Python: >=3.7
License-File: LICENSE
License-File: AUTHORS
Requires-Dist: Kivy-Garden (>=0.1.4)
Requires-Dist: docutils
Requires-Dist: pygments
Requires-Dist: kivy-deps.angle (~=0.3.3) ; sys_platform == "win32"
Requires-Dist: kivy-deps.sdl2 (~=0.6.0) ; sys_platform == "win32"
Requires-Dist: kivy-deps.glew (~=0.3.1) ; sys_platform == "win32"
Requires-Dist: pypiwin32 ; sys_platform == "win32"
Provides-Extra: angle
Requires-Dist: kivy-deps.angle (~=0.3.3) ; (sys_platform == "win32") and extra == 'angle'
Provides-Extra: base
Requires-Dist: pillow ; extra == 'base'
Requires-Dist: requests ; extra == 'base'
Requires-Dist: docutils ; extra == 'base'
Requires-Dist: pygments ; extra == 'base'
Requires-Dist: kivy-deps.angle (~=0.3.3) ; (sys_platform == "win32") and extra == 'base'
Requires-Dist: kivy-deps.sdl2 (~=0.6.0) ; (sys_platform == "win32") and extra == 'base'
Requires-Dist: kivy-deps.glew (~=0.3.1) ; (sys_platform == "win32") and extra == 'base'
Requires-Dist: pypiwin32 ; (sys_platform == "win32") and extra == 'base'
Provides-Extra: dev
Requires-Dist: pytest (>=3.6) ; extra == 'dev'
Requires-Dist: pytest-cov ; extra == 'dev'
Requires-Dist: pytest-asyncio (!=0.11.0) ; extra == 'dev'
Requires-Dist: pytest-timeout ; extra == 'dev'
Requires-Dist: pytest-benchmark ; extra == 'dev'
Requires-Dist: pyinstaller ; extra == 'dev'
Requires-Dist: sphinx (<=6.2.1) ; extra == 'dev'
Requires-Dist: sphinxcontrib-blockdiag ; extra == 'dev'
Requires-Dist: sphinxcontrib-seqdiag ; extra == 'dev'
Requires-Dist: sphinxcontrib-actdiag ; extra == 'dev'
Requires-Dist: sphinxcontrib-nwdiag ; extra == 'dev'
Requires-Dist: funcparserlib (==1.0.0a0) ; extra == 'dev'
Requires-Dist: flake8 ; extra == 'dev'
Requires-Dist: pre-commit ; extra == 'dev'
Requires-Dist: responses ; extra == 'dev'
Requires-Dist: kivy-deps.gstreamer-dev (~=0.3.3) ; (sys_platform == "win32") and extra == 'dev'
Requires-Dist: kivy-deps.sdl2-dev (~=0.6.0) ; (sys_platform == "win32") and extra == 'dev'
Requires-Dist: kivy-deps.glew-dev (~=0.3.1) ; (sys_platform == "win32") and extra == 'dev'
Provides-Extra: full
Requires-Dist: pillow ; extra == 'full'
Requires-Dist: docutils ; extra == 'full'
Requires-Dist: pygments ; extra == 'full'
Requires-Dist: ffpyplayer ; (sys_platform == "linux" or sys_platform == "darwin") and extra == 'full'
Requires-Dist: kivy-deps.gstreamer (~=0.3.3) ; (sys_platform == "win32") and extra == 'full'
Requires-Dist: kivy-deps.angle (~=0.3.3) ; (sys_platform == "win32") and extra == 'full'
Requires-Dist: kivy-deps.sdl2 (~=0.6.0) ; (sys_platform == "win32") and extra == 'full'
Requires-Dist: kivy-deps.glew (~=0.3.1) ; (sys_platform == "win32") and extra == 'full'
Requires-Dist: pypiwin32 ; (sys_platform == "win32") and extra == 'full'
Provides-Extra: glew
Requires-Dist: kivy-deps.glew (~=0.3.1) ; (sys_platform == "win32") and extra == 'glew'
Provides-Extra: gstreamer
Requires-Dist: kivy-deps.gstreamer (~=0.3.3) ; (sys_platform == "win32") and extra == 'gstreamer'
Provides-Extra: media
Requires-Dist: ffpyplayer ; (sys_platform == "linux" or sys_platform == "darwin") and extra == 'media'
Requires-Dist: kivy-deps.gstreamer (~=0.3.3) ; (sys_platform == "win32") and extra == 'media'
Provides-Extra: sdl2
Requires-Dist: kivy-deps.sdl2 (~=0.6.0) ; (sys_platform == "win32") and extra == 'sdl2'
Provides-Extra: tuio
Requires-Dist: oscpy ; extra == 'tuio'
